git_wrapper/__init__.py
git_wrapper/branch.py
git_wrapper/commit.py
git_wrapper/exceptions.py
git_wrapper/log.py
git_wrapper/remote.py
git_wrapper/repo.py
git_wrapper/tag.py
git_wrapper/utils/__init__.py
git_wrapper/utils/decorators.py
git_wrapper-0.2.11.dist-info/licenses/LICENSE
integration_tests/__init__.py
integration_tests/conftest.py
integration_tests/test_branch.py
integration_tests/test_commit.py
integration_tests/test_log.py
integration_tests/test_rebase.py
integration_tests/test_remote.py
integration_tests/test_repo.py
integration_tests/test_tag.py
tests/__init__.py
tests/conftest.py
tests/test_branch.py
tests/test_commit.py
tests/test_log.py
tests/test_remote.py
tests/test_repo.py
tests/test_tag.py
git_wrapper-0.2.11.dist-info/METADATA
git_wrapper-0.2.11.dist-info/WHEEL
git_wrapper-0.2.11.dist-info/top_level.txt
git_wrapper-0.2.11.dist-info/RECORD
