Metadata-Version: 2.4
Name: git_wrapper
Version: 0.2.11
Summary: Python commodity wrapper around GitPython
Home-page: https://github.com/release-depot/git_wrapper
Author: Jason Joyce
Author-email: jjoyce@redhat.com
License: MIT
Project-URL: Bug Tracker, https://github.com/release-depot/git_wrapper/issues
Keywords: git_wrapper
Classifier: Development Status :: 3 - Alpha
Classifier: Intended Audience :: Developers
Classifier: License :: OSI Approved :: MIT License
Classifier: Natural Language :: English
Classifier: Programming Language :: Python :: 3
License-File: LICENSE
Requires-Dist: GitPython
Requires-Dist: wrapt
Provides-Extra: devbase
Requires-Dist: tox; extra == "devbase"
Provides-Extra: test
Requires-Dist: flake8; extra == "test"
Requires-Dist: mock>=2.0.0; extra == "test"
Requires-Dist: pytest; extra == "test"
Requires-Dist: pytest-cov; extra == "test"
Requires-Dist: pytest-datadir; extra == "test"
Requires-Dist: pytest-runner; extra == "test"
Provides-Extra: docs
Requires-Dist: sphinx; extra == "docs"
Requires-Dist: sphinx-autobuild; extra == "docs"
Requires-Dist: sphinx-rtd-theme; extra == "docs"
Requires-Dist: myst-parser; extra == "docs"
Provides-Extra: dist
Requires-Dist: build; extra == "dist"
Requires-Dist: setuptools_scm; extra == "dist"
Requires-Dist: twine; extra == "dist"
Dynamic: license-file
